sws/__init__.py
sws/__main__.py
sws/cli.py
sws/dns_utilities.py
sws/domains.py
sws/downloads.py
sws/redirects.py
sws/ssl_utilities.py
sws/youtube.py
sws-0.2.2.dist-info/LICENSE
sws-0.2.2.dist-info/METADATA
sws-0.2.2.dist-info/WHEEL
sws-0.2.2.dist-info/entry_points.txt
sws-0.2.2.dist-info/top_level.txt
sws-0.2.2.dist-info/RECORD
