Metadata-Version: 2.1
Name: sws
Version: 0.2.2
Summary: An API & command line interface, for common web tasks
Home-page: UNKNOWN
Author: Kieran Wood
Author-email: kieran@canadiancoding.ca
License: UNKNOWN
Project-URL: API Docs, http://kieranwood.ca/sws
Project-URL: CLI Docs, http://sws.readthedocs.io/
Project-URL: Bug Reports, https://github.com/Descent098/sws/issues/new?assignees=Descent098&labels=bug&template=bug_report.md&title=%5BBUG%5D
Project-URL: Source, https://github.com/Descent098/sws
Project-URL: Roadmap, https://github.com/Descent098/sws/projects
Platform: UNKNOWN
Classifier: Programming Language :: Python :: 3
Classifier: License :: OSI Approved :: MIT License
Classifier: Operating System :: OS Independent
Classifier: Development Status :: 4 - Beta
License-File: LICENSE
Requires-Dist: requests
Requires-Dist: pytube
Requires-Dist: docopt
Requires-Dist: pystall
Requires-Dist: python-whois-extended
Requires-Dist: dnspython
Requires-Dist: locust
Requires-Dist: sdu
Provides-Extra: dev
Requires-Dist: nox ; extra == 'dev'
Requires-Dist: pytest ; extra == 'dev'
Requires-Dist: mkdocs ; extra == 'dev'
